{"startSite": "", "filingNum": "", "onePageListNum": 15, "commentLabelColor": "#006b75", "yearColorList": ["#bc4c00", "#0969da", "#1f883d", "#A333D0"], "i18n": "CN", "dayTheme": "light", "nightTheme": "dark", "urlMode": "pinyin", "title": "ielsewhere", "displayTitle": "ielsewhere.log", "subTitle": "\u6743\u529b\u5982\u4e0d\u53d7\u7ea6\u675f\uff0c\u5fc5\u5c06\u4f5c\u6076", "homeUrl": "https:logs.ielsewhere.com", "avatarUrl": "http://meekdai.com/avatar.jpg", "faviconUrl": "http://meekdai.com/favicon.ico", "singlePage": [], "GMEEK_VERSION": "last", "postListJson": {"P2": {"htmlDir": "docs/post/xie-zuo-shi-you-gao-ji-de-kuai-le-gan-de-dong-xi.html", "label": "\u8f6f\u4ef6", "labelColor": "#C28949", "postTitle": "\u5199\u4f5c\u662f\u6709\u9ad8\u7ea7\u7684\u5feb\u4e50\u611f\u7684\u4e1c\u897f", "postUrl": "post/xie-zuo-shi-you-gao-ji-de-kuai-le-gan-de-dong-xi.html", "postSourceUrl": "https://github.com/leoshcn/leoshcn.github.io/issues/2", "commentNum": 0, "description": "\u786e\u5b9e\u662f\u8fd9\u6837\uff0c\u521b\u9020\u5c31\u662f\u53ef\u4ee5\u8ba9\u4eba\u66f4\u5feb\u4e50\u7684\u8fc7\u7a0b\u3002", "top": 0, "createdAt": 1701489405, "style": "", "script": "", "createdDate": "2023-12-02", "dateLabelColor": "#A333D0"}, "P4": {"htmlDir": "docs/post/wei-shen-me-yi-zhi-bu-cheng-gong.html", "label": "\u8f6f\u4ef6", "labelColor": "#C28949", "postTitle": "\u4e3a\u4ec0\u4e48\u4e00\u76f4\u4e0d\u6210\u529f", "postUrl": "post/wei-shen-me-yi-zhi-bu-cheng-gong.html", "postSourceUrl": "https://github.com/leoshcn/leoshcn.github.io/issues/4", "commentNum": 0, "description": "- \u6ce8\u610f\u8981\u5199 labels\r\n- Issue \u5185\u5bb9\u4e0d\u53ef\u4e3a\u7a7a\r\n- \u5fc5\u8981\u65f6\u91cd\u65b0\u8ba9 github actions build \u4e00\u904d\u3002", "top": 0, "createdAt": 1701489866, "style": "", "script": "", "createdDate": "2023-12-02", "dateLabelColor": "#A333D0"}}, "singeListJson": {}, "prevUrl": "disabled", "nextUrl": "disabled"}